{
  "wallpaper": "/home/diaz/Pictures/Wallpapers/ethan-hoover-eIVJAkj1uCs-unsplash.jpg",
  "mode": "dark",
  "variant": "content",
  "source_color": "#162022",
  "colors": {
    "m3primary": "#bec8cb",
    "m3onPrimary": "#283234",
    "m3primaryContainer": "#162022",
    "m3onPrimaryContainer": "#7d888a",
    "m3primaryFixed": "#dae4e7",
    "m3primaryFixedDim": "#bec8cb",
    "m3onPrimaryFixed": "#131d1f",
    "m3onPrimaryFixedVariant": "#3e494b",
    "m3secondary": "#c4c7c8",
    "m3onSecondary": "#2d3132",
    "m3secondaryContainer": "#464a4b",
    "m3onSecondaryContainer": "#b6b9ba",
    "m3secondaryFixed": "#e0e3e4",
    "m3secondaryFixedDim": "#c4c7c8",
    "m3onSecondaryFixed": "#181c1d",
    "m3onSecondaryFixedVariant": "#444748",
    "m3tertiary": "#bec8cb",
    "m3onTertiary": "#283234",
    "m3tertiaryContainer": "#162022",
    "m3onTertiaryContainer": "#7d888a",
    "m3tertiaryFixed": "#dae4e7",
    "m3tertiaryFixedDim": "#bec8cb",
    "m3onTertiaryFixed": "#131d1f",
    "m3onTertiaryFixedVariant": "#3e494b",
    "m3error": "#ffb4ab",
    "m3onError": "#690005",
    "m3errorContainer": "#93000a",
    "m3onErrorContainer": "#ffdad6",
    "m3surface": "#131313",
    "m3onSurface": "#e4e2e1",
    "m3surfaceVariant": "#434849",
    "m3onSurfaceVariant": "#c3c7c8",
    "m3surfaceDim": "#131313",
    "m3surfaceBright": "#393939",
    "m3surfaceContainerLowest": "#0e0e0e",
    "m3surfaceContainerLow": "#1b1c1c",
    "m3surfaceContainer": "#1f2020",
    "m3surfaceContainerHigh": "#2a2a2a",
    "m3surfaceContainerHighest": "#353535",
    "m3background": "#131313",
    "m3onBackground": "#e4e2e1",
    "m3outline": "#8d9192",
    "m3outlineVariant": "#434849",
    "m3inverseSurface": "#e4e2e1",
    "m3inverseOnSurface": "#303030",
    "m3inversePrimary": "#566062",
    "m3shadow": "#000000",
    "m3scrim": "#000000",
    "term0": "#131313",
    "term1": "#690005",
    "term2": "#434849",
    "term3": "#3e494b",
    "term4": "#283234",
    "term5": "#353535",
    "term6": "#464a4b",
    "term7": "#566062",
    "term8": "#e4e2e1",
    "term9": "#ffb4ab",
    "term10": "#dae4e7",
    "term11": "#dae4e7",
    "term12": "#bec8cb",
    "term13": "#bec8cb",
    "term14": "#bec8cb",
    "term15": "#e4e2e1",
    "m3primary_rgb": "190,200,203",
    "m3onPrimary_rgb": "40,50,52",
    "m3primaryContainer_rgb": "22,32,34",
    "m3onPrimaryContainer_rgb": "125,136,138",
    "m3primaryFixed_rgb": "218,228,231",
    "m3primaryFixedDim_rgb": "190,200,203",
    "m3onPrimaryFixed_rgb": "19,29,31",
    "m3onPrimaryFixedVariant_rgb": "62,73,75",
    "m3secondary_rgb": "196,199,200",
    "m3onSecondary_rgb": "45,49,50",
    "m3secondaryContainer_rgb": "70,74,75",
    "m3onSecondaryContainer_rgb": "182,185,186",
    "m3secondaryFixed_rgb": "224,227,228",
    "m3secondaryFixedDim_rgb": "196,199,200",
    "m3onSecondaryFixed_rgb": "24,28,29",
    "m3onSecondaryFixedVariant_rgb": "68,71,72",
    "m3tertiary_rgb": "190,200,203",
    "m3onTertiary_rgb": "40,50,52",
    "m3tertiaryContainer_rgb": "22,32,34",
    "m3onTertiaryContainer_rgb": "125,136,138",
    "m3tertiaryFixed_rgb": "218,228,231",
    "m3tertiaryFixedDim_rgb": "190,200,203",
    "m3onTertiaryFixed_rgb": "19,29,31",
    "m3onTertiaryFixedVariant_rgb": "62,73,75",
    "m3error_rgb": "255,180,171",
    "m3onError_rgb": "105,0,5",
    "m3errorContainer_rgb": "147,0,10",
    "m3onErrorContainer_rgb": "255,218,214",
    "m3surface_rgb": "19,19,19",
    "m3onSurface_rgb": "228,226,225",
    "m3surfaceVariant_rgb": "67,72,73",
    "m3onSurfaceVariant_rgb": "195,199,200",
    "m3surfaceDim_rgb": "19,19,19",
    "m3surfaceBright_rgb": "57,57,57",
    "m3surfaceContainerLowest_rgb": "14,14,14",
    "m3surfaceContainerLow_rgb": "27,28,28",
    "m3surfaceContainer_rgb": "31,32,32",
    "m3surfaceContainerHigh_rgb": "42,42,42",
    "m3surfaceContainerHighest_rgb": "53,53,53",
    "m3background_rgb": "19,19,19",
    "m3onBackground_rgb": "228,226,225",
    "m3outline_rgb": "141,145,146",
    "m3outlineVariant_rgb": "67,72,73",
    "m3inverseSurface_rgb": "228,226,225",
    "m3inverseOnSurface_rgb": "48,48,48",
    "m3inversePrimary_rgb": "86,96,98",
    "m3shadow_rgb": "0,0,0",
    "m3scrim_rgb": "0,0,0",
    "term0_rgb": "19,19,19",
    "term1_rgb": "105,0,5",
    "term2_rgb": "67,72,73",
    "term3_rgb": "62,73,75",
    "term4_rgb": "40,50,52",
    "term5_rgb": "53,53,53",
    "term6_rgb": "70,74,75",
    "term7_rgb": "86,96,98",
    "term8_rgb": "228,226,225",
    "term9_rgb": "255,180,171",
    "term10_rgb": "218,228,231",
    "term11_rgb": "218,228,231",
    "term12_rgb": "190,200,203",
    "term13_rgb": "190,200,203",
    "term14_rgb": "190,200,203",
    "term15_rgb": "228,226,225",
    "m3primary_hypr": "rgba(bec8cbff)",
    "m3onPrimary_hypr": "rgba(283234ff)",
    "m3primaryContainer_hypr": "rgba(162022ff)",
    "m3onPrimaryContainer_hypr": "rgba(7d888aff)",
    "m3primaryFixed_hypr": "rgba(dae4e7ff)",
    "m3primaryFixedDim_hypr": "rgba(bec8cbff)",
    "m3onPrimaryFixed_hypr": "rgba(131d1fff)",
    "m3onPrimaryFixedVariant_hypr": "rgba(3e494bff)",
    "m3secondary_hypr": "rgba(c4c7c8ff)",
    "m3onSecondary_hypr": "rgba(2d3132ff)",
    "m3secondaryContainer_hypr": "rgba(464a4bff)",
    "m3onSecondaryContainer_hypr": "rgba(b6b9baff)",
    "m3secondaryFixed_hypr": "rgba(e0e3e4ff)",
    "m3secondaryFixedDim_hypr": "rgba(c4c7c8ff)",
    "m3onSecondaryFixed_hypr": "rgba(181c1dff)",
    "m3onSecondaryFixedVariant_hypr": "rgba(444748ff)",
    "m3tertiary_hypr": "rgba(bec8cbff)",
    "m3onTertiary_hypr": "rgba(283234ff)",
    "m3tertiaryContainer_hypr": "rgba(162022ff)",
    "m3onTertiaryContainer_hypr": "rgba(7d888aff)",
    "m3tertiaryFixed_hypr": "rgba(dae4e7ff)",
    "m3tertiaryFixedDim_hypr": "rgba(bec8cbff)",
    "m3onTertiaryFixed_hypr": "rgba(131d1fff)",
    "m3onTertiaryFixedVariant_hypr": "rgba(3e494bff)",
    "m3error_hypr": "rgba(ffb4abff)",
    "m3onError_hypr": "rgba(690005ff)",
    "m3errorContainer_hypr": "rgba(93000aff)",
    "m3onErrorContainer_hypr": "rgba(ffdad6ff)",
    "m3surface_hypr": "rgba(131313ff)",
    "m3onSurface_hypr": "rgba(e4e2e1ff)",
    "m3surfaceVariant_hypr": "rgba(434849ff)",
    "m3onSurfaceVariant_hypr": "rgba(c3c7c8ff)",
    "m3surfaceDim_hypr": "rgba(131313ff)",
    "m3surfaceBright_hypr": "rgba(393939ff)",
    "m3surfaceContainerLowest_hypr": "rgba(0e0e0eff)",
    "m3surfaceContainerLow_hypr": "rgba(1b1c1cff)",
    "m3surfaceContainer_hypr": "rgba(1f2020ff)",
    "m3surfaceContainerHigh_hypr": "rgba(2a2a2aff)",
    "m3surfaceContainerHighest_hypr": "rgba(353535ff)",
    "m3background_hypr": "rgba(131313ff)",
    "m3onBackground_hypr": "rgba(e4e2e1ff)",
    "m3outline_hypr": "rgba(8d9192ff)",
    "m3outlineVariant_hypr": "rgba(434849ff)",
    "m3inverseSurface_hypr": "rgba(e4e2e1ff)",
    "m3inverseOnSurface_hypr": "rgba(303030ff)",
    "m3inversePrimary_hypr": "rgba(566062ff)",
    "m3shadow_hypr": "rgba(000000ff)",
    "m3scrim_hypr": "rgba(000000ff)",
    "term0_hypr": "rgba(131313ff)",
    "term1_hypr": "rgba(690005ff)",
    "term2_hypr": "rgba(434849ff)",
    "term3_hypr": "rgba(3e494bff)",
    "term4_hypr": "rgba(283234ff)",
    "term5_hypr": "rgba(353535ff)",
    "term6_hypr": "rgba(464a4bff)",
    "term7_hypr": "rgba(566062ff)",
    "term8_hypr": "rgba(e4e2e1ff)",
    "term9_hypr": "rgba(ffb4abff)",
    "term10_hypr": "rgba(dae4e7ff)",
    "term11_hypr": "rgba(dae4e7ff)",
    "term12_hypr": "rgba(bec8cbff)",
    "term13_hypr": "rgba(bec8cbff)",
    "term14_hypr": "rgba(bec8cbff)",
    "term15_hypr": "rgba(e4e2e1ff)"
  }
}